{
    "user_id": "70943a10",
    "user_name": "Sophie_Z",
    "items": [
        {
            "product_id": "934e0bb6",
            "name": "Women's Summer Casual Linen-Blend Shorts",
            "quantity": 1,
            "price": 249.99
        },
        {
            "product_id": "ef923a8d",
            "name": "Women's Summer Utility Shorts",
            "quantity": 1,
            "price": 429.9
        },
        {
            "product_id": "c5f6c1c7",
            "name": "Women's Gamma Insulated Softshell Pants",
            "quantity": 1,
            "price": 3899.0
        },
        {
            "product_id": "44467c6d",
            "name": "Women's VECTIV™ Terra Trail Shoes",
            "quantity": 1,
            "price": 998.0
        },
        {
            "product_id": "e3992fcc",
            "name": "Puma Kids' Essential Logo Hoodie",
            "quantity": 1,
            "price": 249.9
        },
        {
            "product_id": "e0edc9e4",
            "name": "Gucci Rhyton Leather Platform Sneaker",
            "quantity": 1,
            "price": 7800.0
        }
    ],
    "used_coupons": [],
    "summary": {
        "total_items_count": 6,
        "total_price": 13626.79
    }
}