{
    "user_id": "70e52530",
    "user_name": "SophieChen",
    "items": [
        {
            "product_id": "4f5c4b2e",
            "name": "Women's V-Neck Long Sleeve Knit Top",
            "quantity": 1,
            "price": 249.9
        },
        {
            "product_id": "84adb57f",
            "name": "Women's HOVR Phantom 3 Running Shoes",
            "quantity": 1,
            "price": 899.0
        },
        {
            "product_id": "d13b3fd8",
            "name": "Women's Essentials Logo Fleece Sweatshirt",
            "quantity": 1,
            "price": 359.0
        },
        {
            "product_id": "7db73983",
            "name": "Men's Urban Explorer Windbreaker Jacket",
            "quantity": 1,
            "price": 799.0
        },
        {
            "product_id": "b859d0ba",
            "name": "Women's Essential Tech Fleece Pants",
            "quantity": 1,
            "price": 429.0
        },
        {
            "product_id": "5a4008fa",
            "name": "Women's Essential Ribbed Long-Sleeve Top",
            "quantity": 1,
            "price": 189.0
        }
    ],
    "used_coupons": [],
    "summary": {
        "total_items_count": 6,
        "total_price": 2924.9
    }
}