{
    "user_id": "09c11502",
    "user_name": "长安老李",
    "items": [
        {
            "product_id": "e49a1938",
            "name": "Men's Classic 574 Core Sneakers",
            "quantity": 1,
            "price": 699.0
        },
        {
            "product_id": "6751f98f",
            "name": "Men's TerraFlex Hiking Shoes",
            "quantity": 1,
            "price": 1299.0
        },
        {
            "product_id": "85b13128",
            "name": "Men's AirSense Canvas Sneakers",
            "quantity": 1,
            "price": 249.0
        },
        {
            "product_id": "84475a89",
            "name": "Li-Ning Men's Breathe-Easy Training Top",
            "quantity": 1,
            "price": 229.0
        },
        {
            "product_id": "00c93880",
            "name": "Men's Soft Touch Crew Neck Long-Sleeve T-Shirt",
            "quantity": 1,
            "price": 149.0
        }
    ],
    "used_coupons": [],
    "summary": {
        "total_items_count": 5,
        "total_price": 2625.0
    }
}