{
    "user_id": "a5c63687",
    "username": "SunnyQingdao",
    "phone_number": "13853218899",
    "is_vip": true,
    "demographics": {
        "gender": "Female",
        "age": 26,
        "birthday": "1999-08-20"
    },
    "body_profile": {
        "height_cm": 168,
        "weight_kg": 52,
        "preference_fit": "Loose Fit (Oversize)",
        "standard_sizes": {
            "tops": "XL",
            "bottoms": "M",
            "shoes": "39"
        }
    },
    "coupons": {},
    "shipping_addresses": {
        "phone": "13853218899",
        "province": "Shandong",
        "city": "Qingdao",
        "detail_address": "Shinan District, Yan'erdao Road No. 1, Building 3, Unit 1, Room 1502"
    }
}