{
  "budget_summary": {
    "transportation": 15612,
    "accommodation": 1184,
    "meals": 632,
    "attractions_and_tickets": 8,
    "other": 0,
    "total_estimated_budget": 15612,
    "currency": "CNY"
  },
  "daily_plans": [
    {
      "day_number": 1,
      "current_city": "from 广州 to 泉州",
      "accommodation": {
        "name": "全季泉州万达酒店",
        "price_per_night": 296
      },
      "activities": [
        {
          "time_slot": "14:15-15:30",
          "type": "travel_intercity_public",
          "details": {
            "mode": "flight",
            "number": "HO7161",
            "from": "白云国际机场",
            "to": "泉州晋江国际机场",
            "cost": 1680
          }
        },
        {
          "time_slot": "15:30-16:00",
          "type": "buffer",
          "details": {
            "description": "下飞机、提取行李"
          }
        },
        {
          "time_slot": "16:00-16:21",
          "type": "travel_city",
          "details": {
            "from": "泉州晋江国际机场",
            "to": "全季泉州万达酒店",
            "distance": "13.95km",
            "duration": "21min",
            "cost": 51
          }
        },
        {
          "time_slot": "16:21-16:40",
          "type": "hotel",
          "details": {
            "activity": "办理入住",
            "name": "全季泉州万达酒店"
          }
        },
        {
          "time_slot": "16:40-16:47",
          "type": "travel_city",
          "details": {
            "from": "全季泉州万达酒店",
            "to": "泉州开元寺",
            "distance": "4.94km",
            "duration": "7min",
            "cost": 20
          }
        },
        {
          "time_slot": "16:47-18:30",
          "type": "attraction",
          "details": {
            "name": "泉州开元寺",
            "city": "泉州",
            "cost": 2
          }
        },
        {
          "time_slot": "18:30-18:35",
          "type": "travel_city",
          "details": {
            "from": "泉州开元寺",
            "to": "渔铺私厨泉州菜",
            "distance": "0.24km",
            "duration": "5min",
            "cost": 0
          }
        },
        {
          "time_slot": "18:35-19:35",
          "type": "meal",
          "details": {
            "meal_type": "晚餐",
            "name": "渔铺私厨泉州菜",
            "cost": 69
          }
        },
        {
          "time_slot": "19:35-19:42",
          "type": "travel_city",
          "details": {
            "from": "渔铺私厨泉州菜",
            "to": "全季泉州万达酒店",
            "distance": "4.87km",
            "duration": "7min",
            "cost": 20
          }
        },
        {
          "time_slot": "19:42-24:00",
          "type": "hotel",
          "details": {
            "activity": "休息",
            "name": "全季泉州万达酒店"
          }
        }
      ]
    },
    {
      "day_number": 2,
      "current_city": "泉州",
      "accommodation": {
        "name": "全季泉州万达酒店",
        "price_per_night": 296
      },
      "activities": [
        {
          "time_slot": "08:00-08:52",
          "type": "travel_city",
          "details": {
            "from": "全季泉州万达酒店",
            "to": "安平桥",
            "distance": "34.57km",
            "duration": "52min",
            "cost": 134
          }
        },
        {
          "time_slot": "08:52-10:00",
          "type": "buffer",
          "details": {
            "description": "抵达安平桥，开放时间09:00，等待入园"
          }
        },
        {
          "time_slot": "10:00-12:00",
          "type": "attraction",
          "details": {
            "name": "安平桥",
            "city": "泉州",
            "cost": 0
          }
        },
        {
          "time_slot": "12:00-12:11",
          "type": "travel_city",
          "details": {
            "from": "安平桥",
            "to": "大拇指快餐厅(安平店)",
            "distance": "0.93km",
            "duration": "11min",
            "cost": 0
          }
        },
        {
          "time_slot": "12:11-13:00",
          "type": "meal",
          "details": {
            "meal_type": "午餐",
            "name": "大拇指快餐厅(安平店)",
            "cost": 24
          }
        },
        {
          "time_slot": "13:00-13:53",
          "type": "travel_city",
          "details": {
            "from": "大拇指快餐厅(安平店)",
            "to": "全季泉州万达酒店",
            "distance": "35.02km",
            "duration": "53min",
            "cost": 136
          }
        },
        {
          "time_slot": "13:53-14:05",
          "type": "travel_city",
          "details": {
            "from": "全季泉州万达酒店",
            "to": "中国闽台缘博物馆",
            "distance": "7.96km",
            "duration": "12min",
            "cost": 29
          }
        },
        {
          "time_slot": "14:05-16:30",
          "type": "attraction",
          "details": {
            "name": "中国闽台缘博物馆",
            "city": "泉州",
            "cost": 0
          }
        },
        {
          "time_slot": "16:30-16:46",
          "type": "travel_city",
          "details": {
            "from": "中国闽台缘博物馆",
            "to": "第一餐厅(信息学院第一食堂)",
            "distance": "1.36km",
            "duration": "16min",
            "cost": 0
          }
        },
        {
          "time_slot": "16:46-17:46",
          "type": "meal",
          "details": {
            "meal_type": "晚餐",
            "name": "第一餐厅(信息学院第一食堂)",
            "cost": 36
          }
        },
        {
          "time_slot": "17:46-18:00",
          "type": "travel_city",
          "details": {
            "from": "第一餐厅(信息学院第一食堂)",
            "to": "全季泉州万达酒店",
            "distance": "9.25km",
            "duration": "14min",
            "cost": 33
          }
        },
        {
          "time_slot": "18:00-24:00",
          "type": "hotel",
          "details": {
            "activity": "休息",
            "name": "全季泉州万达酒店"
          }
        }
      ]
    },
    {
      "day_number": 3,
      "current_city": "from 泉州 to 广州",
      "activities": [
        {
          "time_slot": "08:00-08:21",
          "type": "travel_city",
          "details": {
            "from": "全季泉州万达酒店",
            "to": "泉州晋江国际机场",
            "distance": "13.95km",
            "duration": "21min",
            "cost": 51
          }
        },
        {
          "time_slot": "08:21-09:20",
          "type": "buffer",
          "details": {
            "description": "抵达机场，办理值机、安检、候机"
          }
        },
        {
          "time_slot": "09:20-11:20",
          "type": "travel_intercity_public",
          "details": {
            "mode": "flight",
            "number": "NS8385",
            "from": "泉州晋江国际机场",
            "to": "白云国际机场",
            "cost": 1530
          }
        },
        {
          "time_slot": "11:20-13:00",
          "type": "buffer",
          "details": {
            "description": "抵达广州白云国际机场，行程结束"
          }
        }
      ]
    }
  ]
}