{
  "budget_summary": {
    "transportation": 2597,
    "accommodation": 1556,
    "meals": 862,
    "attractions_and_tickets": 150,
    "other": 0,
    "total_estimated_budget": 5299,
    "currency": "CNY"
  },
  "daily_plans": [
    {
      "day_number": 1,
      "current_city": "from 呼和浩特 to 厦门",
      "accommodation": {
        "name": "厦门牡丹国际大酒店",
        "price_per_night": 389
      },
      "activities": [
        {
          "time_slot": "15:30-21:15",
          "type": "travel_intercity_public",
          "details": {
            "mode": "flight",
            "number": "SC2280",
            "from": "呼和浩特白塔国际机场",
            "to": "厦门高崎国际机场",
            "cost": 800
          }
        },
        {
          "time_slot": "21:15-21:45",
          "type": "buffer",
          "details": {
            "description": "下飞机、提取行李"
          }
        },
        {
          "time_slot": "21:45-22:00",
          "type": "travel_city",
          "details": {
            "from": "厦门高崎国际机场",
            "to": "厦门牡丹国际大酒店",
            "distance": "9.78km",
            "duration": "15min",
            "cost": 35
          }
        },
        {
          "time_slot": "22:00-22:15",
          "type": "hotel",
          "details": {
            "activity": "办理入住",
            "name": "厦门牡丹国际大酒店"
          }
        },
        {
          "time_slot": "22:15-24:00",
          "type": "hotel",
          "details": {
            "activity": "休息",
            "name": "厦门牡丹国际大酒店"
          }
        }
      ]
    },
    {
      "day_number": 2,
      "current_city": "厦门",
      "accommodation": {
        "name": "厦门牡丹国际大酒店",
        "price_per_night": 389
      },
      "activities": [
        {
          "time_slot": "07:30-07:43",
          "type": "travel_city",
          "details": {
            "from": "厦门牡丹国际大酒店",
            "to": "厦门大学思明校区",
            "distance": "8.84km",
            "duration": "13min",
            "cost": 32
          }
        },
        {
          "time_slot": "07:43-11:00",
          "type": "attraction",
          "details": {
            "name": "厦门大学思明校区",
            "city": "厦门",
            "cost": 0
          }
        },
        {
          "time_slot": "11:00-11:10",
          "type": "travel_city",
          "details": {
            "from": "厦门大学思明校区",
            "to": "厦门大学思明校区南光餐厅",
            "distance": "0.5km",
            "duration": "10min",
            "cost": 0
          }
        },
        {
          "time_slot": "11:10-12:10",
          "type": "meal",
          "details": {
            "meal_type": "午餐",
            "name": "厦门大学思明校区南光餐厅",
            "cost": 10
          }
        },
        {
          "time_slot": "12:10-12:20",
          "type": "travel_city",
          "details": {
            "from": "厦门大学思明校区南光餐厅",
            "to": "胡里山炮台",
            "distance": "0.5km",
            "duration": "10min",
            "cost": 0
          }
        },
        {
          "time_slot": "12:20-14:30",
          "type": "attraction",
          "details": {
            "name": "胡里山炮台",
            "city": "厦门",
            "cost": 25
          }
        },
        {
          "time_slot": "14:30-14:35",
          "type": "travel_city",
          "details": {
            "from": "胡里山炮台",
            "to": "白城沙滩",
            "distance": "0.5km",
            "duration": "5min",
            "cost": 0
          }
        },
        {
          "time_slot": "14:35-18:00",
          "type": "attraction",
          "details": {
            "name": "白城沙滩",
            "city": "厦门",
            "cost": 0
          }
        },
        {
          "time_slot": "18:00-18:13",
          "type": "travel_city",
          "details": {
            "from": "白城沙滩",
            "to": "鑫鑫落日海景海鲜餐厅(胡里山炮台地标店)",
            "distance": "1km",
            "duration": "13min",
            "cost": 0
          }
        },
        {
          "time_slot": "18:13-19:20",
          "type": "meal",
          "details": {
            "meal_type": "晚餐",
            "name": "鑫鑫落日海景海鲜餐厅(胡里山炮台地标店)",
            "cost": 93
          }
        },
        {
          "time_slot": "19:20-19:34",
          "type": "travel_city",
          "details": {
            "from": "鑫鑫落日海景海鲜餐厅(胡里山炮台地标店)",
            "to": "厦门牡丹国际大酒店",
            "distance": "9.17km",
            "duration": "14min",
            "cost": 33
          }
        },
        {
          "time_slot": "19:34-24:00",
          "type": "hotel",
          "details": {
            "activity": "休息",
            "name": "厦门牡丹国际大酒店"
          }
        }
      ]
    },
    {
      "day_number": 3,
      "current_city": "厦门",
      "accommodation": {
        "name": "厦门牡丹国际大酒店",
        "price_per_night": 389
      },
      "activities": [
        {
          "time_slot": "07:30-07:48",
          "type": "travel_city",
          "details": {
            "from": "厦门牡丹国际大酒店",
            "to": "鼓浪屿码头",
            "distance": "12km",
            "duration": "18min",
            "cost": 45
          }
        },
        {
          "time_slot": "07:48-08:10",
          "type": "buffer",
          "details": {
            "description": "购票、候船"
          }
        },
        {
          "time_slot": "08:10-08:30",
          "type": "travel_city",
          "details": {
            "from": "鼓浪屿码头",
            "to": "鼓浪屿",
            "distance": "",
            "duration": "",
            "cost": 0
          }
        },
        {
          "time_slot": "08:30-10:30",
          "type": "attraction",
          "details": {
            "name": "日光岩",
            "city": "厦门",
            "cost": 50
          }
        },
        {
          "time_slot": "10:30-10:38",
          "type": "travel_city",
          "details": {
            "from": "日光岩",
            "to": "龙头路小吃街",
            "distance": "0.67km",
            "duration": "8min",
            "cost": 0
          }
        },
        {
          "time_slot": "10:38-12:30",
          "type": "attraction",
          "details": {
            "name": "龙头路小吃街",
            "city": "厦门",
            "cost": 0
          }
        },
        {
          "time_slot": "12:30-13:30",
          "type": "meal",
          "details": {
            "meal_type": "午餐",
            "name": "龙头路小吃街",
            "cost": 50
          }
        },
        {
          "time_slot": "13:30-13:40",
          "type": "travel_city",
          "details": {
            "from": "龙头路小吃街",
            "to": "鼓浪屿码头",
            "distance": "0.5km",
            "duration": "10min",
            "cost": 0
          }
        },
        {
          "time_slot": "13:40-14:00",
          "type": "travel_city",
          "details": {
            "from": "鼓浪屿",
            "to": "厦门码头",
            "distance": "",
            "duration": "",
            "cost": 0
          }
        },
        {
          "time_slot": "14:00-14:15",
          "type": "travel_city",
          "details": {
            "from": "厦门码头",
            "to": "厦门牡丹国际大酒店",
            "distance": "12km",
            "duration": "15min",
            "cost": 45
          }
        },
        {
          "time_slot": "14:15-18:00",
          "type": "hotel",
          "details": {
            "activity": "休息",
            "name": "厦门牡丹国际大酒店"
          }
        },
        {
          "time_slot": "18:00-18:09",
          "type": "travel_city",
          "details": {
            "from": "厦门牡丹国际大酒店",
            "to": "曾厝垵",
            "distance": "5.8km",
            "duration": "9min",
            "cost": 23
          }
        },
        {
          "time_slot": "18:09-20:00",
          "type": "attraction",
          "details": {
            "name": "曾厝垵",
            "city": "厦门",
            "cost": 0
          }
        },
        {
          "time_slot": "20:00-21:00",
          "type": "meal",
          "details": {
            "meal_type": "晚餐",
            "name": "曾厝垵内自行觅食",
            "cost": 65
          }
        },
        {
          "time_slot": "21:00-21:09",
          "type": "travel_city",
          "details": {
            "from": "曾厝垵",
            "to": "厦门牡丹国际大酒店",
            "distance": "5.8km",
            "duration": "9min",
            "cost": 23
          }
        },
        {
          "time_slot": "21:09-24:00",
          "type": "hotel",
          "details": {
            "activity": "休息",
            "name": "厦门牡丹国际大酒店"
          }
        }
      ]
    },
    {
      "day_number": 4,
      "current_city": "厦门",
      "accommodation": {
        "name": "厦门牡丹国际大酒店",
        "price_per_night": 389
      },
      "activities": [
        {
          "time_slot": "09:00-09:09",
          "type": "travel_city",
          "details": {
            "from": "厦门牡丹国际大酒店",
            "to": "曾厝垵",
            "distance": "5.8km",
            "duration": "9min",
            "cost": 23
          }
        },
        {
          "time_slot": "09:09-12:00",
          "type": "attraction",
          "details": {
            "name": "曾厝垵",
            "city": "厦门",
            "cost": 0
          }
        },
        {
          "time_slot": "12:00-12:39",
          "type": "travel_city",
          "details": {
            "from": "曾厝垵",
            "to": "黄厝海滩",
            "distance": "5.84km",
            "duration": "9min",
            "cost": 23
          }
        },
        {
          "time_slot": "12:39-15:00",
          "type": "attraction",
          "details": {
            "name": "黄厝海滩",
            "city": "厦门",
            "cost": 0
          }
        },
        {
          "time_slot": "15:00-15:09",
          "type": "travel_city",
          "details": {
            "from": "黄厝海滩",
            "to": "厦门牡丹国际大酒店",
            "distance": "5.88km",
            "duration": "9min",
            "cost": 23
          }
        },
        {
          "time_slot": "15:09-18:00",
          "type": "hotel",
          "details": {
            "activity": "休息",
            "name": "厦门牡丹国际大酒店"
          }
        },
        {
          "time_slot": "18:00-18:15",
          "type": "travel_city",
          "details": {
            "from": "厦门牡丹国际大酒店",
            "to": "中山路步行街",
            "distance": "9.9km",
            "duration": "15min",
            "cost": 35
          }
        },
        {
          "time_slot": "18:15-20:00",
          "type": "attraction",
          "details": {
            "name": "中山路步行街",
            "city": "厦门",
            "cost": 0
          }
        },
        {
          "time_slot": "20:00-21:00",
          "type": "meal",
          "details": {
            "meal_type": "晚餐",
            "name": "中山路步行街附近自行觅食",
            "cost": 80
          }
        },
        {
          "time_slot": "21:00-21:15",
          "type": "travel_city",
          "details": {
            "from": "中山路步行街",
            "to": "厦门牡丹国际大酒店",
            "distance": "9.9km",
            "duration": "15min",
            "cost": 35
          }
        },
        {
          "time_slot": "21:15-24:00",
          "type": "hotel",
          "details": {
            "activity": "休息",
            "name": "厦门牡丹国际大酒店"
          }
        }
      ]
    },
    {
      "day_number": 5,
      "current_city": "from 厦门 to 呼和浩特",
      "activities": [
        {
          "time_slot": "08:00-08:15",
          "type": "travel_city",
          "details": {
            "from": "厦门牡丹国际大酒店",
            "to": "中山路步行街",
            "distance": "9.9km",
            "duration": "15min",
            "cost": 35
          }
        },
        {
          "time_slot": "08:15-11:00",
          "type": "attraction",
          "details": {
            "name": "中山路步行街",
            "city": "厦门",
            "cost": 0
          }
        },
        {
          "time_slot": "11:00-11:10",
          "type": "travel_city",
          "details": {
            "from": "中山路步行街",
            "to": "临家闽南菜(环岛路店)",
            "distance": "0.5km",
            "duration": "10min",
            "cost": 0
          }
        },
        {
          "time_slot": "11:10-12:10",
          "type": "meal",
          "details": {
            "meal_type": "午餐",
            "name": "临家闽南菜(环岛路店)",
            "cost": 100
          }
        },
        {
          "time_slot": "12:10-12:33",
          "type": "travel_city",
          "details": {
            "from": "临家闽南菜(环岛路店)",
            "to": "厦门高崎国际机场",
            "distance": "15.6km",
            "duration": "23min",
            "cost": 58
          }
        },
        {
          "time_slot": "12:33-13:05",
          "type": "buffer",
          "details": {
            "description": "抵达机场，办理值机、安检、候机"
          }
        },
        {
          "time_slot": "13:05-17:55",
          "type": "travel_intercity_public",
          "details": {
            "mode": "flight",
            "number": "MF8159",
            "from": "厦门高崎国际机场",
            "to": "呼和浩特白塔国际机场",
            "cost": 800
          }
        },
        {
          "time_slot": "17:55-18:15",
          "type": "buffer",
          "details": {
            "description": "下飞机，返程回家"
          }
        }
      ]
    }
  ]
}