{
    "user_id": "d77295a9",
    "user_name": "皖皖晴天",
    "items": [
        {
            "product_id": "505ac420",
            "name": "Li-Ning 'Silver Flash' Pro Running Shoes",
            "quantity": 1,
            "price": 1199.0
        },
        {
            "product_id": "4c4c7cc0",
            "name": "Women's Classic Canvas Low-Top Sneakers",
            "quantity": 1,
            "price": 378.0
        },
        {
            "product_id": "448e1992",
            "name": "Women's Heritage Logo Pullover Sweatshirt",
            "quantity": 1,
            "price": 865.0
        },
        {
            "product_id": "336d786f",
            "name": "Levi's Women's Heritage Leather Ankle Boots",
            "quantity": 1,
            "price": 957.0
        }
    ],
    "used_coupons": [
        {
            "coupon_name": "Cross-store: ¥300 off every ¥1,500",
            "quantity": 2
        }
    ],
    "summary": {
        "total_items_count": 4,
        "total_price": 2799.0
    }
}